blobBgone/__init__.py
blobBgone/eval.py
blobBgone/featureHandler.py
blobBgone/features.py
blobBgone/features2D.py
blobBgone/features3D.py
blobBgone/utils.py
blobBgone-0.2.1.dist-info/LICENSE
blobBgone-0.2.1.dist-info/METADATA
blobBgone-0.2.1.dist-info/WHEEL
blobBgone-0.2.1.dist-info/top_level.txt
blobBgone-0.2.1.dist-info/RECORD
